{
    "id": 61531210,
    "name": "Hyper Paradox",
    "aredl": "#473",
    "author": "ItsHybrid",
    "creators": ["Avati", "Temp", "ViralDL", "El3ctr0", "SyQual", "Realvet", "Connected", "ItsHybrid"],
    "verifier": "BastianAK",
    "verification": "https://youtu.be/LM6DuQ99FPU",
    "percentToQualify": 100,
    "password": "251326",
    "records": [
        {
            "user": "NotJellyGD",
            "link": "https://youtu.be/gvAjBDMEZfY?si=3bjr9rODtc6UYVoT",
            "percent": 100,
            "hz": 480
        },
        {
            "user": "Dornoc429",
            "link": "https://youtu.be/dlbSbsWRWNI?si=v4xKibXRXzAuiPF2",
            "percent": 100,
            "hz": 240
        },
        {
            "user": "Sanctuary",
            "link": "https://youtu.be/1WUlNoWBgFk?si=c-n_SqVdFb_e-GLv",
            "percent": 100,
            "hz": 240
        }
    ]
}
