{
    "id": 81372683,
    "name": "RANDOM ACCESS MEMORY",
    "aredl": "#232",
    "author": "Acute",
    "creators": ["Zeronium", "Valentine", "Krisz", "kreno", "oleki", "Trunith", "Acute", "OliSW", "AAAAAlex", "SleyGD"],
    "verifier": "Lucidium",
    "verification": "https://www.youtube.com/watch?v=2F3rYuzhyYA",
    "percentToQualify": 100,
    "password": "Free to Copy",
    "records": [
        {
            "user": "Ka1b3ast",
            "link": "https://youtu.be/4jBMC88Rc8Q?si=CNLoCDRA7rYilHwZ",
            "percent": 100,
            "hz": 240
        }
    ]
}
