{
    "id": 51584312,
    "name": "super probably level",
    "aredl": "#309",
    "author": "Alkali",
    "creators": [],
    "verifier": "Camicorder",
    "verification": "https://youtu.be/nNMaAF0ErMs",
    "percentToQualify": "100",
    "password": "Free To Copy",
    "records": [
        {
            "user": "Aless50",
            "link": "https://www.youtube.com/watch?v=wh7F0yYvlaI",
            "percent": 100,
            "hz": 480
        },
        {
            "user": "CraZDemonX",
            "link": "https://youtu.be/Zb7TRJjbegI?si=7Y6yfsLIkNzWVse0",
            "percent": 100,
            "hz": 240
        }
    ]
}
