{
    "id": 71434979,
    "name": "Trueffet",
    "aredl": "#75",
    "author": "SyQual",
    "creators": ["SyQual", "Rainstorm"],
    "verifier": "xaern",
    "verification": "https://www.youtube.com/watch?v=9VfiIgC8N3I",
    "percentToQualify": 100,
    "password": "Free to Copy",
    "records": [
        {
            "user": "Lucidium",
            "link": "https://youtu.be/_9XQpbb1udk",
            "percent": 100,
            "hz": 240
        },
        {
            "user": "funnypoop1",
            "link": "https://youtu.be/sz1mYLFs5ig?si=VTffJuKuCiyi3QnJ",
            "percent": 100,
            "hz": 240
        },
        {
            "user": "geodom",
            "link": "https://youtu.be/_DxsBwq1XyI?si=r_oHakuWq99oppoZ",
            "percent": 100,
            "hz": 240
        }
    ]
}
